README.md
setup.cfg
setup.py
multacdkrecipies/__init__.py
multacdkrecipies.egg-info/PKG-INFO
multacdkrecipies.egg-info/SOURCES.txt
multacdkrecipies.egg-info/dependency_links.txt
multacdkrecipies.egg-info/requires.txt
multacdkrecipies.egg-info/top_level.txt
multacdkrecipies/common/__init__.py
multacdkrecipies/common/framework_constructs/__init__.py
multacdkrecipies/common/framework_constructs/base_trigger.py
multacdkrecipies/common/resources_constructs/__init__.py
multacdkrecipies/common/resources_constructs/alarms.py
multacdkrecipies/common/resources_constructs/bucket.py
multacdkrecipies/common/resources_constructs/cognito_user_groups.py
multacdkrecipies/common/resources_constructs/cognito_user_identity_pool.py
multacdkrecipies/common/resources_constructs/cognito_user_pool.py
multacdkrecipies/common/resources_constructs/dynamo_table.py
multacdkrecipies/common/resources_constructs/iot_analytics_channel.py
multacdkrecipies/common/resources_constructs/iot_analytics_datastore.py
multacdkrecipies/common/resources_constructs/iot_analytics_pipeline.py
multacdkrecipies/common/resources_constructs/iot_analytics_sql_dataset.py
multacdkrecipies/common/resources_constructs/iot_rule.py
multacdkrecipies/common/resources_constructs/kinesis_firehose_delivery_stream.py
multacdkrecipies/common/resources_constructs/kinesis_stream.py
multacdkrecipies/common/resources_constructs/lambda_function.py
multacdkrecipies/common/resources_constructs/lambda_layer.py
multacdkrecipies/common/resources_constructs/queue.py
multacdkrecipies/common/resources_constructs/role.py
multacdkrecipies/common/resources_constructs/topic.py
multacdkrecipies/common/validations/__init__.py
multacdkrecipies/common/validations/base_validations.py
multacdkrecipies/framework/__init__.py
multacdkrecipies/framework/checkers/__init__.py
multacdkrecipies/framework/connectors/__init__.py
multacdkrecipies/framework/connectors/active/__init__.py
multacdkrecipies/framework/connectors/passive/__init__.py
multacdkrecipies/framework/formatters/__init__.py
multacdkrecipies/framework/parsers/__init__.py
multacdkrecipies/framework/settings/__init__.py
multacdkrecipies/framework/triggers/__init__.py
