Metadata-Version: 2.1
Name: multacdkrecipies
Version: 0.2.0.5
Summary: A CDK Python Construct for AWS IoT Infrastructure
Home-page: https://github.com/u93/multacdkrecipies
Author: Eugenio Efrain Breijo
Author-email: eebf1993@gmail.com
Maintainer: Eugenio Efrain Breijo
Maintainer-email: eebf1993@gmail.com
License: MIT
Keywords: aws,aws-cdk,cdk,infrastructure,cloudformation,python,resources_constructs,framework
Platform: UNKNOWN
Classifier: Development Status :: 4 - Beta
Classifier: Environment :: MacOS X
Classifier: Intended Audience :: Developers
Classifier: Intended Audience :: Education
Classifier: Intended Audience :: Information Technology
Classifier: Intended Audience :: System Administrators
Classifier: License :: OSI Approved :: MIT License
Classifier: Natural Language :: English
Classifier: Operating System :: MacOS :: MacOS X
Classifier: Operating System :: POSIX :: Linux
Classifier: Programming Language :: Python :: 3 :: Only
Classifier: Programming Language :: Python :: 3.7
Classifier: Topic :: Internet :: WWW/HTTP
Classifier: Topic :: Software Development
Classifier: Topic :: Software Development :: Code Generators
Classifier: Topic :: Software Development :: Libraries :: Application Frameworks
Classifier: Topic :: Utilities
Classifier: Typing :: Typed
Requires-Python: >=3.7
